Metadata-Version: 2.1
Name: flask-rest-crud
Version: 0.3.0
Summary: Generate full CRUD from mongoengine models
Home-page: https://github.com/rafaelcorradini/flask-rest-crud
Author: Rafael Corradini da Cunha
Author-email: rafacunhadini@gmail.com
License: MIT
Keywords: flask,mongoengine,crud,rest
Platform: UNKNOWN
Classifier: Development Status :: 3 - Alpha
Classifier: Intended Audience :: Developers
Classifier: Topic :: Software Development :: Build Tools
Classifier: License :: OSI Approved :: MIT License
Classifier: Programming Language :: Python :: 3
Classifier: Programming Language :: Python :: 3.4
Classifier: Programming Language :: Python :: 3.5
Classifier: Programming Language :: Python :: 3.6
Classifier: Programming Language :: Python :: 3.7
Classifier: Programming Language :: Python :: 3.8
